{"en":{"concepts":{"RF_FO_LAMA_12":"RF_FO_LAMA","SUSPECTED_TB_6":"Suspected TB","SAM_6":"SAM","DIARRHEA_WITH_DEHYDRATION_6":"Diarrhea with dehydration","CLINICAL_MALARIA_6":"Clinical Malaria","MEASLES_6":"Measles","GLOBAL_DOCTORS_NAME_1_14":"GLOBAL_Doctors_Name_1","LABOUR_PAINS_REFERRED_6":"Labour Pains referred","SEVERE_JAUNDICE_6":"Severe Jaundice","DIARRHEA_WITH_SOME_DEHYDRATION_6":"Diarrhea with some dehydration","UTI_6":"UTI","RF_INST_GITANJALI_7":"RF_Inst_Gitanjali","CONFIRMED_TB_SPUTUM_POSITIVE_CAT_2_6":"Confirmed TB Sputum Positive Cat 2","JAUNDICE_6":"Jaundice","GLOBAL_DOCTORS_NAME_14":"Doctor's Name","DMPA_COMPLICATIONS_6":"DMPA Complications","FEEDING_PROBLEM_6":"Feeding problem","NO_PNEUMONIA_COUGH_AND_COLD_6":"No pneumonia cough and cold","MALARIA_FALCIPARUM_6":"Malaria falciparum","MYALGIA-NON_SPECIFIC_BODYACHE_6":"Myalgia-non specific bodyache","SEVERE_MEASLES_6":"Severe Measles","RF_REASON_6":"Reason for referral","HYPERTENSION_6":"Hypertension","SKIN_DISEASE-_DERMATITIS_6":"Skin disease- Dermatitis","GLOBAL_DOCTORS_NAME_4_14":"GLOBAL_Doctors_Name_4","RF_INST_MB_7":"RF_Inst_MB","MENSTRUAL_DISORDERS_6":"Menstrual Disorders","ASTHMA_6":"Asthma","CATARACT_6":"Cataract","GLOBAL_NURSE_NAME1_15":"GLOBAL_Nurse_Name1","SKIN_DISEASE_-_TINEA_6":"Skin Disease - Tinea","PNC-1_COMPLICATIONS_6":"PNC-1 Complications","GLOBAL_DATE_TIME_2":"Referral Date and Time","RF_DATE_OF_SCHEDULED_5":"Date of scheduled referral","SKIN_DISEASES-FUNGAL_6":"Skin diseases-Fungal","UNDERNUTRITION_6":"Undernutrition","RF_ACCEPTING_DATE_TIME_10":"Date and Time of accepting referral","LOW_BIRTH_WEIGHT_WITH_NO_COMPLICATIONS_6":"Low birth weight with no complications","RF_EMERGENCY_4":"RF_Emergency","PNEUMONIA_6":"Pneumonia","GLOBAL_NURSE_NAME2_15":"GLOBAL_Nurse_Name2","DIARRHEA_WITH_SEVERE_DEHYDRATION_6":"Diarrhea with severe dehydration","SKIN_DISEASE_-_OTHERS_6":"Skin Disease - Others","LOW_BIRTH_WEIGHT_WITH_COMPLICATIONS_6":"Low birth weight with complications","SKIN_DISEASE_-_IMPETIGO_6":"Skin Disease - Impetigo","WANTS_TERMINATION_OF_PREGNANCY_6":"Wants termination of pregnancy","DMPA_FIRST_6":"DMPA First","PELIVIC_INFLAMMATORY_DISEASE_6":"Pelivic Inflammatory disease","SKIN_DISEASE-OTHER_6":"Skin Disease-Other","GLOBAL_NURSE_NAME_15":"Nurse's Name","RF_VEHICLE_USED_11":"Vehicle used","LOW_BODY_TEMPERATURE_6":"Low body temperature","RF_TYPE_OF_REFERRAL_4":"Type of referral","DYSENTRY_6":"Dysentry","SKIN_DISEASE-IMPETIGO_6":"Skin Disease-Impetigo","RF_OTHER_INSTITUTION_8":"Other Institution","MEDICAL_ABORTION_WITH_COMPLICATION_6":"Medical Abortion with complication","RF_104_11":"RF_104","RF_OUTCOME_SECTION_13":"Referral outcome","RF_DETAILS_SECTION_3":"Referral details","BABY_DELIVERED-FOLLOW-UP_6":"Baby delivered-Follow-up","GLOBAL_DOCTORS_NAME_2_14":"GLOBAL_Doctors_Name_2","SKIN_DISEASE-FUNGAL_6":"Skin Disease-Fungal","MENSTRUAL_DISORDER-MENORRHAGIA_IRREGULAR_INTERMENSTRUAL_BLEEDING_6":"Menstrual Disorder-Menorrhagia_Irregular_Intermenstrual Bleeding","CONFIRMED_MALARIA_FALCIPARUM_6":"Confirmed Malaria Falciparum","CATARACT_SURGERY_6":"Cataract Surgery","INJURY_WITH_STITCHES_6":"Injury with stitches","LABOUR_PAINS_6":"Labour Pains","RF_FO_DISCHARGED_SATISFACTORY_12":"RF_FO_Discharged_Satisfactory","MALARIA_-MIXED_6":"Malaria -mixed","SEPTICAEMIA_6":"Septicaemia","OSTEOARTHRITIS_6":"Osteoarthritis","ORAL_CONTRACEPTIVES_6":"Oral Contraceptives","ENTERIC_FEVER_6":"Enteric Fever","PELVIC_INFLAMMATORY_DISEASE_6":"Pelvic Inflammatory Disease","MALARIA_VIVAX_6":"Malaria Vivax","SEVERE_PNEUMONIA_6":"Severe pneumonia","CONFIRMED_TB_SPUTUM_NEGATIVE_CAT_2_6":"Confirmed TB sputum negative Cat 2","RHEUMATIC_HEART_DISEASE-RHD_6":"Rheumatic Heart Disease-RHD","NORMAL_BIRTH_WEIGHT_WITH_COMPLICATIONS_6":"Normal birth weight with complications","EXTRA-PULMONARY_TB_CAT_2_6":"Extra-pulmonary TB Cat 2","GLOBAL_DOCTORS_NAME_5_14":"GLOBAL_Doctors_Name_5","PNC-2_COMPLICATIONS_6":"PNC-2 Complications","CONFIRMED_TB_6":"Confirmed TB","CHRONIC_EAR_INFECTION_6":"Chronic ear infection","ANEMIA_6":"Anemia","LEPROSY,_TEMPLATE_6":"Leprosy, Template","CHRONIC_BRONCHITIS_6":"Chronic Bronchitis","LOCAL_BACTERIAL_INFECTION_6":"Local Bacterial Infection","RF_INST_OTHERS_7":"RF_Inst_Others","RF_INST_ALAKH_NAYAN_7":"RF_Inst_Alakh Nayan","RF_FINAL_OUTCOME_12":"Final outcome","SKIN_DISEASE_-_SCABIES_6":"Skin Disease - Scabies","CONFIRMED_MALARIA_MIXED_6":"Confirmed Malaria Mixed","ACUTE_EAR_INFECTION_6":"Acute ear infection","ANAEMIA_6":"Anaemia","SEVERE_UNDERNUTRITION_6":"Severe undernutrition","SKIN_DISEASE-SCABIES_6":"Skin Disease-Scabies","SKIN_DISEASE-DERMATITIS_6":"Skin disease-dermatitis","WANTS_CONTRACEPTION_6":"Wants Contraception","RF_FO_DIS_NOT_SATISFACTORY_12":"RF_FO_Dis_Not_Satisfactory","CHRONIC_LUNG_DISEASE_6":"Chronic Lung disease","CONFIRMATION_OF_PREGNANCY_6":"Confirmation of pregnancy","NORMAL_BIRTH_WEIGHT_WITH_NO_COMPLICATIONS_6":"Normal birth weight with no complications","EXTRA-PULMONARY_TB_CAT_1_6":"Extra-pulmonary TB Cat 1","REPRODUCTIVE_TRACT_INFECTION_6":"Reproductive Tract Infection","GLOBAL_DOCTORS_NAME_3_14":"GLOBAL_Doctors_Name_3","RF_AMRIT_AMBULANCE_11":"RF_AMRIT_Ambulance","TB Prophylaxis_6":"TB Prophylaxis","CONFIRMED_TB_SPUTUM_NEGATIVE_CAT_1_6":"Confirmed TB sputum Negative Cat 1","URI_6":"URI","RF_INST_CHC_7":"RF_Inst_CHC","PNC-3_COMPLICATIONS_6":"PNC-3 Complications","MALNUTRITION_DIAGNOSIS_6":"Malnutrition Diagnosis","RF_108_11":"RF_108","NO_FEEDING_PROBLEM_6":"No feeding problem","CONFIRMED_TB_SPUTUM_POSITIVE_CAT_1_6":"Confirmed TB Sputum Positive Cat 1","DIABETES_AND_HYPERTENSION_6":"Diabetes and Hypertension","LOWER_RESPIRATORY_TRACT_INFECTION_6":"Lower Respiratory Tract Infection","RF_ACCEPTED_REFERRAL_9":"Accepted referral","RF_PRIVATE_VEHICLE_11":"RF_Private vehicle","RF_SCHEDULED_4":"RF_Scheduled","DYSENTERY_6":"Dysentery","RF_INSTITUTE_NAME_7":"Name of institution referred to","INJURY_WITHOUT_STICHES_6":"Injury without stiches","PERSISTENT_DIARRHEA_6":"Persistent diarrhea","DIARRHEA_WITH_NO_DEHYDRATION_6":"Diarrhea with no dehydration","BABY_DELIVERED_6":"Baby Delivered","DIABETES_6":"Diabetes","CONFIRMED_MALARIA_VIVAX_6":"Confirmed Malaria Vivax","RF_FO_DEATH_12":"RF_FO_Death","ACUTE_OTITIS_MEDIA_6":"Acute Otitis Media","GASTRITIS_6":"Gastritis","DMPA_SUBSEQUENT_6":"DMPA Subsequent","SEVERE_ANEMIA_6":"Severe anemia","INFERTILITY_6":"Infertility"},"labels":{"BOOLEAN_NO":"No","BOOLEAN_YES":"Yes"}}}